convbnmerge/__init__.py
convbnmerge/convbnmerge.py
convbnmerge-0.1.6.dist-info/LICENSE
convbnmerge-0.1.6.dist-info/METADATA
convbnmerge-0.1.6.dist-info/WHEEL
convbnmerge-0.1.6.dist-info/top_level.txt
convbnmerge-0.1.6.dist-info/RECORD
